zeropy/__init__.py
zeropy/client.py
zeropy/logger.py
zeropy/proto.py
zeropy/protoutil.py
zeropy/socket.py
zeropy/structs.py
zeropy/utils.py
zeropy-0.4.0.dist-info/LICENSE
zeropy-0.4.0.dist-info/METADATA
zeropy-0.4.0.dist-info/WHEEL
zeropy-0.4.0.dist-info/top_level.txt
zeropy-0.4.0.dist-info/RECORD
