Metadata-Version: 2.1
Name: zeropy
Version: 0.4.0
Summary: zerolevel blockchain's api bind.
Home-page: UNKNOWN
Author: zerolevel team
Author-email: zerolevel@gmail.com
License: UNKNOWN
Platform: UNKNOWN
Classifier: Programming Language :: Python :: 3
Classifier: License :: OSI Approved
Classifier: Operating System :: OS Independent
Requires-Dist: zerocrypt (==0.2)
Requires-Dist: crcpy (==0.1)
